asyncswagger11/__init__.py
asyncswagger11/client.py
asyncswagger11/codegen.py
asyncswagger11/http_client.py
asyncswagger11/processors.py
asyncswagger11/swagger_model.py
asyncswagger11-0.20.0.dist-info/licenses/LICENSE.txt
asyncswagger11-0.20.0.dist-info/METADATA
asyncswagger11-0.20.0.dist-info/WHEEL
asyncswagger11-0.20.0.dist-info/top_level.txt
asyncswagger11-0.20.0.dist-info/RECORD
