Metadata-Version: 2.4
Name: asyncswagger11
Version: 0.20.0
Summary: Asynchronous library for accessing Swagger-1.1-enabled APIs
Author-email: Matt Jordan <mjordan@digium.com>, Matthias Urlichs <matthias@urlichs.de>
License: Copyright (c) 2013, Digium, Inc.
Project-URL: Homepage, https://github.com/M-o-a-T/asyncswagger11
Keywords: swagger
Classifier: Development Status :: 4 - Beta
Classifier: Intended Audience :: Developers
Classifier: Topic :: Software Development :: Libraries :: Python Modules
Classifier: License :: OSI Approved :: BSD License
Classifier: Operating System :: OS Independent
Classifier: Programming Language :: Python :: 3
License-File: LICENSE.txt
Requires-Dist: httpx
Provides-Extra: test
Requires-Dist: mocket; extra == "test"
Requires-Dist: pytest; extra == "test"
Dynamic: license-file
